rlmc/__init__.py
rlmc/configs/__init__.py
rlmc/configs/common_urls.yaml
rlmc/configs/permissions.yaml
rlmc/configs/script_paths.yaml
rlmc/configs/user_setting.yaml
rlmc/configs/datasets/__init__.py
rlmc/configs/datasets/dataset_download_urls.yaml
rlmc/configs/models/__init__.py
rlmc/configs/models/model_download_urls.yaml
rlmc/configs/trainval/__init__.py
rlmc/configs/trainval/segmantic_segmentation.yaml
rlmc/data/__init__.py
rlmc/data/dataloader_example.py
rlmc/data/semantic_segmentation.py
rlmc/data/utils.py
rlmc/fileop/__init__.py
rlmc/fileop/abstract_file.py
rlmc/fileop/json_op.py
rlmc/fileop/mat_op.py
rlmc/fileop/numpy_op.py
rlmc/fileop/pickle_op.py
rlmc/fileop/tensorflow_ckpt.py
rlmc/fileop/utils.py
rlmc/fileop/video_op.py
rlmc/fileop/yaml_op.py
rlmc/model/__init__.py
rlmc/model/predictor.py
rlmc/model/cv/__init__.py
rlmc/model/cv/semantic_segmentation.py
rlmc/model/cv/timm_models_example.py
rlmc/model/llm/__init__.py
rlmc/model/nlp/__init__.py
rlmc/model/rl/__init__.py
rlmc/resource/__init__.py
rlmc/resource/condarc.txt
rlmc/resource/cudarc.txt
rlmc/resource/pip.ini
rlmc/trainer/__init__.py
rlmc/trainer/loss.py
rlmc/trainer/met.py
rlmc/trainer/opt.py
rlmc/trainer/trainer.py
rlmc/tutorial/c_packages/cython_test/examples_cy.pyx
rlmc/tutorial/c_packages/cython_test/main.py
rlmc/tutorial/c_packages/cython_test/setup.py
rlmc/tutorial/loop/numpyloop.py
rlmc/tutorial/transformer_onlytutorial_notuse/__init__.py
rlmc/tutorial/transformer_onlytutorial_notuse/datasets.py
rlmc/tutorial/transformer_onlytutorial_notuse/main.py
rlmc/tutorial/transformer_onlytutorial_notuse/test.py
rlmc/tutorial/transformer_onlytutorial_notuse/transformer.py
rlmc/utils/__init__.py
rlmc/utils/agents.py
rlmc/utils/agents_coroutine.py
rlmc/utils/assistant.py
rlmc/utils/asynctask.py
rlmc/utils/coroutine.py
rlmc/utils/downloadscript.py
rlmc/utils/gittool.py
rlmc/utils/logger.py
rlmc/utils/login_module.py
rlmc/utils/mc.py
rlmc/utils/multiprocess.py
rlmc/utils/multithread.py
rlmc/utils/register.py
rlmc-1.2.2.dist-info/LICENSE
rlmc-1.2.2.dist-info/METADATA
rlmc-1.2.2.dist-info/WHEEL
rlmc-1.2.2.dist-info/entry_points.txt
rlmc-1.2.2.dist-info/top_level.txt
rlmc-1.2.2.dist-info/RECORD
