Metadata-Version: 2.1
Name: rlmc
Version: 1.2.2
Summary: Python utils for AI 🚀
Author: Ray Lam
Maintainer: Ray Lam
License: Apache-2.0
Project-URL: Source, https://github.com/RayLam2022/rlmc
Keywords: machine-learning,deep-learning,ML,DL,AI
Classifier: Development Status :: 4 - Beta
Classifier: Intended Audience :: Developers
Classifier: Topic :: Software Development :: Build Tools
Classifier: License :: OSI Approved :: Apache Software License
Classifier: Operating System :: POSIX :: Linux
Classifier: Operating System :: MacOS
Classifier: Operating System :: Microsoft :: Windows
Requires-Python: >=3.8
License-File: LICENSE
Requires-Dist: colorlog
Requires-Dist: pyyaml
Requires-Dist: tqdm
Requires-Dist: numpy
Requires-Dist: huggingface-hub
Requires-Dist: scipy
Requires-Dist: scikit-learn
Requires-Dist: opencv-python
Requires-Dist: pillow
Requires-Dist: rich
Requires-Dist: requests
Requires-Dist: aiohttp
Requires-Dist: aiofiles
Requires-Dist: beautifulsoup4
Requires-Dist: lxml
Requires-Dist: python-dotenv
Requires-Dist: pydantic
Requires-Dist: tifffile
Requires-Dist: psutil
Requires-Dist: networkx
Provides-Extra: assistant
Requires-Dist: pyaudio; extra == "assistant"
Requires-Dist: pyttsx3; extra == "assistant"
Requires-Dist: ChatTTS; extra == "assistant"
Requires-Dist: pynput; extra == "assistant"
Requires-Dist: pyperclip; extra == "assistant"
Requires-Dist: easyocr; extra == "assistant"
Requires-Dist: wave; extra == "assistant"
Requires-Dist: pyannote.audio; extra == "assistant"
Requires-Dist: faiss-cpu; extra == "assistant"
Requires-Dist: qianfan; extra == "assistant"
Requires-Dist: onnxruntime-gpu; extra == "assistant"
Requires-Dist: funasr; extra == "assistant"
Provides-Extra: chart
Requires-Dist: matplotlib; extra == "chart"
Requires-Dist: pyecharts; extra == "chart"
Requires-Dist: streamlit; extra == "chart"
Requires-Dist: streamlit-echarts; extra == "chart"
Requires-Dist: fastexcel; extra == "chart"
Requires-Dist: polars; extra == "chart"
Provides-Extra: dev
Requires-Dist: pytest; extra == "dev"
Requires-Dist: mypy; extra == "dev"
Requires-Dist: build; extra == "dev"
Requires-Dist: twine; extra == "dev"
Provides-Extra: download
Requires-Dist: modelscope; extra == "download"
Requires-Dist: codewithgpu; extra == "download"
Provides-Extra: game
Requires-Dist: pygame; extra == "game"
Requires-Dist: gym; extra == "game"
Provides-Extra: git
Requires-Dist: gitpython; extra == "git"
Provides-Extra: handcontrol
Requires-Dist: pycaw; extra == "handcontrol"
Requires-Dist: mediapipe; extra == "handcontrol"
Requires-Dist: comtypes; extra == "handcontrol"
Requires-Dist: pynput; extra == "handcontrol"
Provides-Extra: jax
Requires-Dist: jax; extra == "jax"
Requires-Dist: jaxlib; extra == "jax"
Provides-Extra: jupyterlab
Requires-Dist: jupyterlab; extra == "jupyterlab"
Provides-Extra: paddle
Requires-Dist: paddlepaddle; extra == "paddle"
Requires-Dist: paddlehub; extra == "paddle"
Provides-Extra: tensorflow
Requires-Dist: h5py; extra == "tensorflow"
Requires-Dist: tensorflow-gpu==2.7.0; extra == "tensorflow"
Requires-Dist: keras; extra == "tensorflow"
Provides-Extra: torch
Requires-Dist: torch; extra == "torch"
Requires-Dist: torchvision; extra == "torch"
Requires-Dist: torchaudio; extra == "torch"
Requires-Dist: xformers; extra == "torch"
Requires-Dist: soundfile; extra == "torch"
Requires-Dist: transformers; extra == "torch"
Requires-Dist: timm; extra == "torch"
Requires-Dist: segmentation-models-pytorch; extra == "torch"
Requires-Dist: torchsummary; extra == "torch"
Requires-Dist: thop; extra == "torch"
Requires-Dist: supervision; extra == "torch"
Requires-Dist: einops; extra == "torch"
Requires-Dist: zhconv; extra == "torch"
Requires-Dist: zhon; extra == "torch"
Requires-Dist: pypinyin; extra == "torch"
Requires-Dist: safetensors; extra == "torch"
Requires-Dist: librosa; extra == "torch"
Provides-Extra: video
Requires-Dist: av; extra == "video"
Requires-Dist: pyaudio; extra == "video"
Requires-Dist: moviepy; extra == "video"
Requires-Dist: srt; extra == "video"
Provides-Extra: web
Requires-Dist: selenium; extra == "web"
Requires-Dist: streamlit; extra == "web"
Requires-Dist: streamlit-echarts; extra == "web"
Requires-Dist: gradio; extra == "web"
Requires-Dist: fastapi; extra == "web"
